yt_dlp_mcp/__init__.py
yt_dlp_mcp/server.py
yt_dlp_mcp-0.2.0.dist-info/METADATA
yt_dlp_mcp-0.2.0.dist-info/WHEEL
yt_dlp_mcp-0.2.0.dist-info/entry_points.txt
yt_dlp_mcp-0.2.0.dist-info/top_level.txt
yt_dlp_mcp-0.2.0.dist-info/RECORD
