Metadata-Version: 2.4
Name: yt-dlp-mcp
Version: 0.2.0
Summary: MCP server for YouTube video operations using yt-dlp
Author-email: Gavin Huang <noreply@github.com>
License-Expression: MIT
Project-URL: Homepage, https://github.com/gavinHuang/yt-dlp-mcp
Project-URL: Repository, https://github.com/gavinHuang/yt-dlp-mcp
Project-URL: Issues, https://github.com/gavinHuang/yt-dlp-mcp/issues
Keywords: mcp,youtube,yt-dlp,video,transcription
Classifier: Development Status :: 4 - Beta
Classifier: Intended Audience :: Developers
Classifier: Programming Language :: Python :: 3
Classifier: Programming Language :: Python :: 3.8
Classifier: Programming Language :: Python :: 3.9
Classifier: Programming Language :: Python :: 3.10
Classifier: Programming Language :: Python :: 3.11
Classifier: Programming Language :: Python :: 3.12
Classifier: Topic :: Software Development :: Libraries :: Python Modules
Classifier: Topic :: Multimedia :: Video
Requires-Python: >=3.8
Requires-Dist: fastmcp>=0.2.0
Requires-Dist: yt-dlp>=2023.12.30
Provides-Extra: dev
Requires-Dist: pytest; extra == "dev"
Requires-Dist: black; extra == "dev"
Requires-Dist: isort; extra == "dev"
Requires-Dist: mypy; extra == "dev"
